fava/__init__.py
fava/cli.py
fava/core/__init__.py
fava/core/runner.py
fava/core/database/__init__.py
fava/core/database/migration.py
fava/core/database/model.py
fava/core/http/__init__.py
fava/core/http/controller.py
fava/core/http/route.py
fava/core/server/__init__.py
fava/core/server/console.py
fava/core/utils/__init__.py
fava/core/utils/helper.py
fava/core/utils/variables.py
falafel_fava-0.2.3.dist-info/METADATA
falafel_fava-0.2.3.dist-info/WHEEL
falafel_fava-0.2.3.dist-info/entry_points.txt
falafel_fava-0.2.3.dist-info/top_level.txt
falafel_fava-0.2.3.dist-info/RECORD
