Metadata-Version: 2.1
Name: falafel-fava
Version: 0.2.3
Summary: A collection of tools for Falafel Framework (Flask with MVC)
Home-page: https://getfalafel.com/docs/en
Author: Regis Tomkiel
Project-URL: Documentation, https://getfalafel.github.io/docs/en/
Project-URL: Source Code, https://github.com/getfalafel/fava
Project-URL: Issue Tracker, https://github.com/getfalafel/fava/issues/
Project-URL: Twitter, https://twitter.com/tomtomkiel
Classifier: Programming Language :: Python :: 3
Classifier: License :: OSI Approved :: MIT License
Classifier: Operating System :: OS Independent
Requires-Python: >=3.9
Requires-Dist: black
Requires-Dist: toml
Requires-Dist: requests
Requires-Dist: inflect
Requires-Dist: flask
Requires-Dist: Flask-SQLAlchemy
Requires-Dist: flask-marshmallow
Requires-Dist: Flask-Cors
Requires-Dist: SQLAlchemy
Requires-Dist: SQLAlchemy-serializer
Requires-Dist: jwt
Requires-Dist: dynaconf
